cosim/__init__.py
cosim-0.0.0.dist-info/LICENSE
cosim-0.0.0.dist-info/METADATA
cosim-0.0.0.dist-info/WHEEL
cosim-0.0.0.dist-info/top_level.txt
cosim-0.0.0.dist-info/RECORD
